nonebot_plugin_acm_reminder/__init__.py
nonebot_plugin_acm_reminder/config.py
nonebot_plugin_acm_reminder/data_source.py
nonebot_plugin_acm_reminder-0.2.0.dist-info/WHEEL
nonebot_plugin_acm_reminder-0.2.0.dist-info/METADATA
nonebot_plugin_acm_reminder-0.2.0.dist-info/licenses/LICENSE
nonebot_plugin_acm_reminder-0.2.0.dist-info/RECORD
