Metadata-Version: 2.1
Name: nonebot_plugin_acm_reminder
Version: 0.2.0
Summary: A subscribe CodeForces/NowCoder/Atcoder contest info plugin for nonebot2
License: MIT
Author-email: BigOrangeQWQ <2284086963@qq.com>
Requires-Python: >=3.9
Requires-Dist: BeautifulSoup4>=4.12.3
Requires-Dist: httpx>=0.23.3
Requires-Dist: nonebot-plugin-alconna>=0.42.0
Requires-Dist: nonebot-plugin-apscheduler>=0.2.0
Requires-Dist: nonebot-plugin-htmlrender>=0.2.0.3
Requires-Dist: nonebot2>=2.2.1
Requires-Dist: pydantic>=2.6.4
